fastproj/__init__.py
fastproj/main.py
fastproj/{fastproj.project_name}/backend/backend/__init__.py
fastproj/{fastproj.project_name}/docker/backend.dockerfile
fastproj-0.1.0.dist-info/entry_points.txt
fastproj-0.1.0.dist-info/WHEEL
fastproj-0.1.0.dist-info/METADATA
fastproj-0.1.0.dist-info/RECORD
