Metadata-Version: 2.1
Name: fastproj
Version: 0.1.0
Summary: 
Author: Michael Kalashnikov
Author-email: kalashnikovsystem@gmail.com
Requires-Python: >=3.10,<4.0
Classifier: Programming Language :: Python :: 3
Classifier: Programming Language :: Python :: 3.10
Requires-Dist: loguru (>=0.6.0,<0.7.0)
Requires-Dist: typer (>=0.4.0,<0.5.0)
